CHANGES.txt
LICENSE.txt
MANIFEST
MANIFEST.in
PKGBUILD
README.rst
distribute.sh
setup.cfg
setup.py
SamSifter.egg-info/PKG-INFO
SamSifter.egg-info/SOURCES.txt
SamSifter.egg-info/dependency_links.txt
SamSifter.egg-info/entry_points.txt
SamSifter.egg-info/not-zip-safe
SamSifter.egg-info/requires.txt
SamSifter.egg-info/top_level.txt
bin/enrich_summary
docs/Makefile
docs/screenshot_v0.1.0.png
docs/screenshot_v0.png
docs/screenshot_win32_v0.png
docs/build/html/api.html
docs/build/html/genindex.html
docs/build/html/help.html
docs/build/html/index.html
docs/build/html/manual.html
docs/build/html/pmdtools.html
docs/build/html/py-modindex.html
docs/build/html/samsifter.gui.html
docs/build/html/samsifter.html
docs/build/html/samsifter.models.html
docs/build/html/samsifter.resources.html
docs/build/html/samsifter.stats.html
docs/build/html/samsifter.tools.html
docs/build/html/samsifter.util.html
docs/build/html/samsifter.views.html
docs/build/html/search.html
docs/build/html/searchindex.js
docs/build/html/_images/bash_dialog.png
docs/build/html/_images/example_workflow.png
docs/build/html/_images/filters_dock.png
docs/build/html/_images/input_error.png
docs/build/html/_images/messages_dock.png
docs/build/html/_images/output_error.png
docs/build/html/_images/sam2rma_dialog.png
docs/build/html/_images/screenshot_v0.4.1.png
docs/build/html/_images/settings_dock.png
docs/build/html/_images/workflow_progress.png
docs/build/html/_modules/index.html
docs/build/html/_modules/pmdtools/pmdtools_mod.html
docs/build/html/_modules/samsifter/samsifter.html
docs/build/html/_modules/samsifter/gui/composites.html
docs/build/html/_modules/samsifter/gui/dialogs.html
docs/build/html/_modules/samsifter/gui/widgets.html
docs/build/html/_modules/samsifter/models/filter.html
docs/build/html/_modules/samsifter/models/filter_model.html
docs/build/html/_modules/samsifter/models/parameter.html
docs/build/html/_modules/samsifter/models/workflow.html
docs/build/html/_modules/samsifter/stats/compile_stats.html
docs/build/html/_modules/samsifter/stats/summarize_stats.html
docs/build/html/_modules/samsifter/tools/bam_2_sam.html
docs/build/html/_modules/samsifter/tools/calculate_pmds.html
