Metadata-Version: 1.1
Name: SamSifter
Version: 1.0.0
Summary: Workflow editor for metagenomic analysis
Home-page: http://pypi.python.org/pypi/SamSifter/
Author: Florian Aldehoff
Author-email: f.aldehoff@student.uni-tuebingen.de
License: LICENSE.txt
Platform: UNKNOWN
Classifier: Development Status :: 3 - Alpha
Classifier: Environment :: X11 Applications :: Qt
Classifier: Intended Audience :: Science/Research
Classifier: License :: OSI Approved :: GNU General Public License v3 (GPLv3)
Classifier: Natural Language :: English
Classifier: Operating System :: POSIX
Classifier: Programming Language :: Python :: 3 :: Only
Classifier: Topic :: Scientific/Engineering :: Bio-Informatics
